LICENSE
passwrd/__init__.py
passwrd/__main__.py
passwrd/app.py
passwrd-0.1.0.dist-info/LICENSE
passwrd-0.1.0.dist-info/WHEEL
passwrd-0.1.0.dist-info/METADATA
passwrd-0.1.0.dist-info/RECORD
