Metadata-Version: 2.1
Name: passwrd
Version: 0.1.0
Summary: Python tool to generate secure mnemonic passwords.
Home-page: https://github.com/samedamci/passwrd
License: ISC
Author: samedamci
Author-email: samedamci@disroot.org
Classifier: Development Status :: 5 - Production/Stable
Classifier: Intended Audience :: Developers
Classifier: Intended Audience :: End Users/Desktop
Classifier: License :: OSI Approved
Classifier: License :: OSI Approved :: ISC License (ISCL)
Classifier: Programming Language :: Python
Classifier: Programming Language :: Python :: 2
Classifier: Programming Language :: Python :: 2.7
Classifier: Programming Language :: Python :: 3
Classifier: Programming Language :: Python :: 3.4
Classifier: Programming Language :: Python :: 3.5
Classifier: Programming Language :: Python :: 3.6
Classifier: Programming Language :: Python :: 3.7
Classifier: Programming Language :: Python :: 3.8
Classifier: Programming Language :: Python :: 3.9
Classifier: Programming Language :: Python :: Implementation :: CPython
Classifier: Programming Language :: Python :: Implementation :: PyPy
Classifier: Topic :: Security
Classifier: Topic :: Software Development :: Libraries
Classifier: Topic :: Utilities
Classifier: Typing :: Typed
Project-URL: Repository, https://github.com/samedamci/passwrd
